inapp_file_lib/__init__.py
inapp_file_lib/record.py
inapp_file_lib_rjanoop-1.0.3.dist-info/LICENSE
inapp_file_lib_rjanoop-1.0.3.dist-info/METADATA
inapp_file_lib_rjanoop-1.0.3.dist-info/WHEEL
inapp_file_lib_rjanoop-1.0.3.dist-info/top_level.txt
inapp_file_lib_rjanoop-1.0.3.dist-info/RECORD
