Metadata-Version: 2.1
Name: inapp-file-lib-rjanoop
Version: 1.0.3
Summary: Library to read and write raw data file and create dictionary based of definition models
Home-page: https://github.com/rjanoop/inapp_file_lib
Author: RJ Anoop
Author-email: mail.anooprj@gmail.com
License: UNKNOWN
Platform: UNKNOWN
Classifier: Programming Language :: Python :: 3
Classifier: License :: OSI Approved :: MIT License
Classifier: Operating System :: OS Independent
